Metadata-Version: 2.1
Name: lyynircmd
Version: 1.3
Summary: yyjdgui for lyy
Author: lyy
Author-email: 
License: MIT
License-File: LICENSE
